forestly/__init__.py
forestly/core/__init__.py
forestly/core/config.py
forestly/core/forest_plot.py
forestly/exporters/__init__.py
forestly/exporters/reactable.py
forestly/panels/__init__.py
forestly/panels/base.py
forestly/panels/sparkline.py
forestly/panels/text.py
forestly/panels/templates/plotly_deps.js
forestly/panels/templates/sparkline.js
forestly-0.1.2.dist-info/METADATA
forestly-0.1.2.dist-info/WHEEL
forestly-0.1.2.dist-info/licenses/LICENSE
forestly-0.1.2.dist-info/RECORD
