Metadata-Version: 2.4
Name: forestly
Version: 0.1.2
Summary: InteractiveForest Plot
Project-URL: Repository, https://github.com/elong0527/py-forestly
Project-URL: Documentation, https://github.com/elong0527/py-forestly#readme
License: MIT
License-File: LICENSE
Keywords: clinical-trials,forest-plot,plotly,polars,reactable,visualization
Classifier: Development Status :: 4 - Beta
Classifier: Intended Audience :: Healthcare Industry
Classifier: Intended Audience :: Science/Research
Classifier: License :: OSI Approved :: MIT License
Classifier: Programming Language :: Python :: 3
Classifier: Programming Language :: Python :: 3.10
Classifier: Programming Language :: Python :: 3.11
Classifier: Programming Language :: Python :: 3.12
Classifier: Programming Language :: Python :: 3.13
Classifier: Topic :: Scientific/Engineering :: Bio-Informatics
Classifier: Topic :: Scientific/Engineering :: Visualization
Requires-Python: >=3.10
Requires-Dist: jinja2>=3.1.6
Requires-Dist: pandas>=2.3.1
Requires-Dist: plotly>=6.3.0
Requires-Dist: polars>=1.32.3
Requires-Dist: pyarrow>=21.0.0
Requires-Dist: pydantic>=2.11.7
Requires-Dist: reactable>=0.1.5
